pdal_piper/__init__.py
pdal_piper/pdal_piper.py
pdal_piper/skeletons.py
pdal_piper-0.2.2.dist-info/licenses/LICENSE.txt
pdal_piper-0.2.2.dist-info/METADATA
pdal_piper-0.2.2.dist-info/WHEEL
pdal_piper-0.2.2.dist-info/entry_points.txt
pdal_piper-0.2.2.dist-info/top_level.txt
pdal_piper-0.2.2.dist-info/RECORD
