Metadata-Version: 2.4
Name: pdal-piper
Version: 0.2.2
Summary: Type stubs and utilities for PDAL (Point Data Abstraction Library) and USGS 3DEP lidar download.
Author-email: "Johnathan Tenny (j-tenny)" <jt893@nau.edu>
License: MIT
Project-URL: Homepage, https://github.com/j-tenny/pdal-piper
Requires-Python: >=3.9
License-File: LICENSE.txt
Dynamic: license-file
